sgdot/__init__.py
sgdot/grids.py
sgdot/tools/__init__.py
sgdot/tools/grid_optimizer.py
sgdot/tools/grid_visualizer.py
sgdot/tools/io.py
sgdot/tools/optimization.py
sgdot/tools/plot.py
sgdot/tools/sgdot_tools_optimization.py
sgdot/tools/visualization.py
sgdot-1.401.dist-info/LICENCE
sgdot-1.401.dist-info/METADATA
sgdot-1.401.dist-info/WHEEL
sgdot-1.401.dist-info/top_level.txt
sgdot-1.401.dist-info/RECORD
