Metadata-Version: 2.1
Name: sgdot
Version: 1.401
Summary: UNKNOWN
Home-page: UNKNOWN
Author: UNKNOWN
Author-email: UNKNOWN
License: UNKNOWN
Platform: UNKNOWN
Requires-Dist: numpy
Requires-Dist: pandas
Requires-Dist: opencv-python (<=4.2.0.34)
Requires-Dist: configparser
Requires-Dist: munkres
Requires-Dist: scipy
Requires-Dist: pulp
Requires-Dist: sklearn
Requires-Dist: matplotlib
